{"data": {"bnwikisource": {"campaigns": {"damaging_and_goodfaith": {"total": 3799, "done": 0, "id": 66}}}, "fiwiki": {"campaigns": {"damaging_and_goodfaith": {"total": 5423, "done": 2777, "id": 60}}, "models": {"goodfaith": {"version": "0.4.1"}, "damaging": {"version": "0.4.1"}}}, "ukwiki": {"campaigns": {"damaging_and_goodfaith": {"total": 3318, "done": 598, "id": 11}}, "models": {"reverted": {"version": "0.4.0"}}}, "elwiki": {"models": {"reverted": {"version": "0.4.0"}}}, "testwiki": {"models": {"goodfaith": {"version": "0.0.3"}, "reverted": {"version": "0.0.3"}, "damaging": {"version": "0.0.3"}}}, "hewiki": {"campaigns": {"damaging_and_goodfaith": {"total": 5000, "done": 5003, "id": 25}}, "models": {"goodfaith": {"version": "0.4.0"}, "damaging": {"version": "0.4.0"}}}, "fawiki": {"campaigns": {"wp10": {"total": 289, "done": 278, "id": 71}}, "models": {"goodfaith": {"version": "0.4.0"}, "damaging": {"version": "0.4.0"}}}, "ruwiki": {"models": {"wp10": {"version": "0.6.0"}, "goodfaith": {"version": "0.4.0"}, "damaging": {"version": "0.4.0"}}}, "iswiki": {"models": {"reverted": {"version": "0.4.0"}}}, "azwiki": {"campaigns": {"damaging_and_goodfaith": {"total": 4526, "done": 0, "id": 69}}}, "nowiki": {"campaigns": {"damaging_and_goodfaith": {"total": 5000, "done": 2080, "id": 27}}, "models": {"reverted": {"version": "0.4.1"}}}, "zhwiki": {"campaigns": {"damaging_and_goodfaith": {"total": 5000, "done": 5016, "id": 45}}}, "enwiki": {"campaigns": {"damaging_and_goodfaith": {"total": 6333, "done": 3032, "id": 41}}, "models": {"wp10": {"version": "0.6.1"}, "goodfaith": {"version": "0.4.0"}, "draftquality": {"version": "0.1.0"}, "damaging": {"version": "0.4.0"}}}, "bawiki": {"campaigns": {"damaging_and_goodfaith": {"total": 4824, "done": 0, "id": 67}}}, "svwiki": {"campaigns": {"damaging_and_goodfaith": {"total": 5000, "done": 5018, "id": 35}}, "models": {"goodfaith": {"version": "0.4.1"}, "damaging": {"version": "0.4.1"}}}, "viwiki": {"campaigns": {"damaging_and_goodfaith": {"total": 5000, "done": 154, "id": 26}}, "models": {"reverted": {"version": "0.4.0"}}}, "rowiki": {"campaigns": {"damaging_and_goodfaith": {"total": 3650, "done": 3650, "id": 48}}, "models": {"goodfaith": {"version": "0.4.1"}, "damaging": {"version": "0.4.1"}}}, "eswikibooks": {"campaigns": {"damaging_and_goodfaith": {"total": 9495, "done": 9455, "id": 42}}, "models": {"goodfaith": {"version": "0.4.0"}, "damaging": {"version": "0.4.0"}}}, "dewiki": {"campaigns": {"damaging_and_goodfaith": {"total": 4177, "done": 415, "id": 16}}, "models": {"reverted": {"version": "0.4.0"}}}, "etwiki": {"models": {"goodfaith": {"version": "0.4.0"}, "damaging": {"version": "0.4.0"}}}, "eswiki": {"models": {"goodfaith": {"version": "0.4.0"}, "damaging": {"version": "0.4.0"}}}, "kowiki": {"campaigns": {"damaging_and_goodfaith": {"total": 7186, "done": 3904, "id": 50}}, "models": {"reverted": {"version": "0.4.0"}}}, "ptwiki": {"models": {"goodfaith": {"version": "0.4.0"}, "damaging": {"version": "0.4.0"}}}, "hrwiki": {"campaigns": {"damaging_and_goodfaith": {"total": 6724, "done": 1145, "id": 61}}, "models": {"reverted": {"version": "0.4.0"}}}, "enwiktionary": {"campaigns": {"damaging_and_goodfaith": {"total": 4599, "done": 0, "id": 72}}, "models": {"reverted": {"version": "0.4.0"}}}, "lvwiki": {"campaigns": {"damaging_and_goodfaith": {"total": 2654, "done": 2649, "id": 56}}}, "plwiki": {"models": {"goodfaith": {"version": "0.4.0"}, "damaging": {"version": "0.4.0"}}}, "huwiki": {"campaigns": {"damaging_and_goodfaith": {"total": 5000, "done": 5003, "id": 33}}, "models": {"reverted": {"version": "0.4.1"}}}, "srwiki": {"campaigns": {"damaging_and_goodfaith": {"total": 4677, "done": 2990, "id": 62}}}, "jawiki": {"campaigns": {"damaging_and_goodfaith": {"total": 9514, "done": 357, "id": 15}}}, "sqwiki": {"campaigns": {"damaging_and_goodfaith": {"total": 4563, "done": 4590, "id": 57}}, "models": {"goodfaith": {"version": "0.4.0"}, "damaging": {"version": "0.4.0"}}}, "tawiki": {"models": {"reverted": {"version": "0.4.0"}}}, "simplewiki": {"campaigns": {"damaging_and_goodfaith": {"total": 9258, "done": 5070, "id": 63}}, "models": {"wp10": {"version": "0.6.1"}, "goodfaith": {"version": "0.4.0"}, "draftquality": {"version": "0.1.0"}, "damaging": {"version": "0.4.0"}}}, "arwiki": {"campaigns": {"damaging_and_goodfaith": {"total": 4977, "done": 4977, "id": 30}}, "models": {"reverted": {"version": "0.4.1"}}}, "cswiki": {"models": {"goodfaith": {"version": "0.4.0"}, "damaging": {"version": "0.4.0"}}}, "frwikisource": {"models": {"pagelevel": {"version": "0.1.0"}}}, "eswikiquote": {"campaigns": {"damaging_and_goodfaith": {"total": 5149, "done": 299, "id": 64}}, "models": {"reverted": {"version": "0.4.0"}}}, "cawiki": {"campaigns": {"damaging_and_goodfaith": {"total": 4232, "done": 4232, "id": 68}}}, "frwiki": {"campaigns": {"damaging_and_goodfaith": {"total": 5000, "done": 5000, "id": 38}}, "models": {"wp10": {"version": "0.6.0"}, "goodfaith": {"version": "0.4.0"}, "damaging": {"version": "0.4.0"}}}, "wikidatawiki": {"campaigns": {}, "models": {"goodfaith": {"version": "0.4.0"}, "itemquality": {"version": "0.2.0"}, "damaging": {"version": "0.4.0"}}}, "idwiki": {"campaigns": {"damaging_and_goodfaith": {"total": 2200, "done": 107, "id": 13}}, "models": {"reverted": {"version": "0.4.0"}}}, "itwiki": {"campaigns": {"damaging_and_goodfaith": {"total": 5390, "done": 599, "id": 18}, "edit_type": {"total": 100, "done": 138, "id": 29}}, "models": {"reverted": {"version": "0.4.0"}}}, "nlwiki": {"models": {"goodfaith": {"version": "0.4.0"}, "damaging": {"version": "0.4.0"}}}, "bnwiki": {"campaigns": {"damaging_and_goodfaith": {"total": 3001, "done": 104, "id": 65}}, "models": {"reverted": {"version": "0.4.0"}}}, "urwiki": {"campaigns": {"damaging_and_goodfaith": {"total": 5000, "done": 165, "id": 23}}}, "trwiki": {"campaigns": {"damaging_and_goodfaith": {"total": 5918, "done": 503, "id": 54}}, "models": {"wp10": {"version": "0.6.0"}, "goodfaith": {"version": "0.4.0"}, "damaging": {"version": "0.4.0"}}}}, "timestamp": 1522092330.2233949}